{
  "@context": "http://schema.org",
  "@type": "Dataset",
  "@id": "",
  "identifier": "http://gbadske.org:9000/dataportal/",
  "name": "EXAMPLE DATA",
  "about:": "The Global Burden of Animal Disease Informatics Metadata provides information about how data can be accessed via the GBADs API, as well as other relevant information about the data.",
  "creator": [
    {
      "@type": "Organization/Country",
      "name": "Author Name"
    }
  ],
  "contactPoint": [
    {
      "@type": "Organization",
      "name": "The Global Burden of Animal Diseases Informatics",
      "email": "metadata@gbadske.org"
    }
  ],
  "dcmi:periodocity": "Annual",
  "datePublished": "yyyy-mm-dd",
  "description": "Description of dataset",
  "spatialCoverage": "Data are reported by country or organizations?",
  "temporalCoverage": "yyyy/yyyy",
  "keywords": [
    "Add some",
    "related keywords",
    "here"
  ],
  "species": "Species",
  "citation": [
    {
      "text": "",
      "@id": "",
      "identifier": ""
    }
  ],
  "license": {
    "text": "License Info Here",
    "url": ""
  },
  "publisher": {
    "@type": "Organization/Country",
    "name": "publisher"
  },
  "provider": {
    "@type": "Organization/Country",
    "name": "provider"
  },
  "distribution": [
    {
      "@type": "DataDownload",
      "fileFormat": "csv",
      "contentUrl": "Data can be downloaded via the GBADs API. For more information about specific API calls please visit http://gbadske.org:9000/dataportal/"
    }
  ]
}